WTFormsValidation/__init__.py
WTFormsValidation/core.py
WTFormsValidation/default_provider.py
WTFormsValidation/regex_utils.py
WTFormsValidation/tagging/__init__.py
WTFormsValidation/tagging/base.py
WTFormsValidation/tagging/bouncer.py
WTFormsValidation/tagging/parsley.py
WTFormsValidation/tagging/yaireo.py
WTFormsValidation-0.1.0.dist-info/LICENSE
WTFormsValidation-0.1.0.dist-info/METADATA
WTFormsValidation-0.1.0.dist-info/WHEEL
WTFormsValidation-0.1.0.dist-info/top_level.txt
WTFormsValidation-0.1.0.dist-info/RECORD
