Metadata-Version: 2.1
Name: WTFormsValidation
Version: 0.1.0
Summary: A python library for generating client side validation functions from WTForms for various validator libraries.
Home-page: https://github.com/Aresius423/WTFormsValidation
Author: János Márkus
Author-email: aresius423@gmail.com
License: UNKNOWN
Platform: UNKNOWN
Classifier: Programming Language :: Python :: 3
Classifier: License :: OSI Approved :: MIT License
Classifier: Operating System :: OS Independent
Requires-Python: >=3.6
